crsredis/__init__.py
crsredis/crsredis.py
crsredis-1.0.0.dist-info/LICENSE
crsredis-1.0.0.dist-info/METADATA
crsredis-1.0.0.dist-info/WHEEL
crsredis-1.0.0.dist-info/top_level.txt
crsredis-1.0.0.dist-info/RECORD
